{
  "$schema": "https://cloud.uipath.com/draft/2024-12/entry-point",
  "entryPoints": [
    {
      "filePath": "Main.xaml",
      "uniqueId": "5a77d18b-4601-4d89-b3b7-151ab8865a1b",
      "type": "process",
      "input": {
        "type": "object",
        "properties": {
          "in_OrchestratorQueueName": {
            "type": "string"
          },
          "in_OrchestratorQueueFolder": {
            "type": "string"
          }
        },
        "required": []
      }
    }
  ]
}